{
	"class" : {
		"on:" : "monty 11/18/2014 17:18",
		"on:documentURI:" : "monty 12/6/2014 17:03",
		"onFileNamed:" : "monty 1/21/2014 23:36",
		"onURL:" : "monty 12/6/2014 17:02",
		"onURL:upToLimit:" : "monty 12/6/2014 17:01",
		"parse:" : "JAAyer 11/10/2010 05:21",
		"parse:usingNamespaces:" : "JAAyer 11/10/2010 05:30",
		"parse:usingNamespaces:validation:" : "monty 11/15/2013 23:33",
		"parse:usingNamespaces:validation:externalEntities:" : "monty 11/16/2013 07:30",
		"parseDocumentFrom:" : "monty 10/27/2014 12:13",
		"parseFileNamed:" : "JAAyer 11/13/2010 20:43",
		"parseURL:" : "monty 11/15/2013 23:35" },
	"instance" : {
		"attributeDeclaration:name:type:defaultPragma:defaultValue:" : "monty 12/30/2013 23:57",
		"characters:" : "mir 1/8/2002 18:27",
		"comment:" : "JAAyer 11/10/2010 19:23",
		"configuration" : "monty 10/27/2014 09:14",
		"configuration:" : "monty 12/3/2014 11:59",
		"configurationClass" : "JAAyer 11/23/2010 15:35",
		"currentScope:" : "monty 12/27/2013 03:36",
		"defaultDocumentURI" : "monty 1/9/2014 05:28",
		"documentReadLimit" : "monty 1/19/2014 03:51",
		"documentReadLimit:" : "monty 10/3/2014 00:11",
		"documentURI" : "monty 11/15/2013 21:14",
		"driverClass" : "monty 2/9/2014 02:43",
		"elementDeclaration:contentModel:" : "monty 11/13/2013 23:54",
		"endCData" : "JAAyer 2/21/2010 15:13",
		"endCDataSection" : "monty 10/27/2014 14:38",
		"endDTD" : "monty 11/12/2013 18:01",
		"endDocument" : "JAAyer 11/27/2010 06:50",
		"endElement:" : "JAAyer 11/10/2010 19:23",
		"endElement:prefix:uri:" : "JAAyer 3/24/2010 16:50",
		"endElement:prefix:uri:localName:" : "monty 11/14/2013 00:13",
		"endEntity:" : "JAAyer 11/10/2010 19:23",
		"endInternalSubset" : "monty 10/27/2014 14:45",
		"endPrefixMapping:" : "JAA 3/22/2011 11:32",
		"externalEntityResolver" : "monty 12/8/2013 02:33",
		"externalEntityResolver:" : "monty 12/29/2013 01:55",
		"externalSubsetReadLimit" : "monty 1/19/2014 03:52",
		"externalSubsetReadLimit:" : "monty 10/3/2014 00:11",
		"generalEntityDeclaration:publicID:systemID:ndata:" : "monty 11/14/2013 04:01",
		"generalEntityDeclaration:replacement:" : "monty 11/14/2013 04:02",
		"ignorableWhitespace:" : "mir 8/11/2000 16:25",
		"input" : "monty 10/22/2014 03:19",
		"interruptParsing" : "monty 12/3/2014 12:17",
		"isInCDataSection" : "monty 10/27/2014 09:15",
		"isInInternalSubset" : "monty 11/18/2014 01:24",
		"isValidating" : "JAAyer 11/23/2010 14:20",
		"isValidating:" : "monty 12/29/2013 03:00",
		"maxEntityReplacementDepth" : "monty 1/19/2014 03:52",
		"maxEntityReplacementDepth:" : "monty 10/3/2014 00:11",
		"notationDeclaration:publicID:systemID:" : "monty 10/4/2014 03:34",
		"on:" : "monty 11/18/2014 17:17",
		"on:documentURI:" : "monty 12/3/2014 11:58",
		"optimizeForLargeDocuments" : "monty 11/26/2014 01:53",
		"parameterEntityDeclaration:publicID:systemID:" : "monty 11/14/2013 04:05",
		"parameterEntityDeclaration:replacement:" : "monty 11/14/2013 04:05",
		"parseDocument" : "monty 12/3/2014 12:00",
		"parseDocumentUntil:" : "monty 12/3/2014 12:27",
		"parseDocumentWhile:" : "monty 12/3/2014 12:01",
		"parser" : "monty 12/3/2014 12:19",
		"parserClass" : "monty 10/3/2014 00:18",
		"parserLimits" : "monty 1/16/2014 18:46",
		"parsingResult" : "monty 12/4/2014 14:07",
		"preservesUndeclaredEntityReferences" : "monty 12/7/2013 19:18",
		"preservesUndeclaredEntityReferences:" : "monty 12/29/2013 03:01",
		"processingInstruction:data:" : "JAA 3/22/2011 11:31",
		"removeLimits" : "monty 10/3/2014 00:16",
		"requiresDocumentConstraints" : "monty 12/21/2013 20:07",
		"requiresDocumentConstraints:" : "monty 12/29/2013 03:23",
		"resolvesExternalEntities" : "monty 11/16/2013 07:33",
		"resolvesExternalEntities:" : "monty 1/24/2014 23:52",
		"skippedEntity:" : "JAAyer 11/10/2010 19:22",
		"startCData" : "mir 8/11/2000 18:53",
		"startCDataSection" : "monty 10/27/2014 14:38",
		"startDTD:publicID:systemID:" : "JAAyer 11/10/2010 19:21",
		"startDocument" : "mir 8/11/2000 16:45",
		"startElement:attributes:" : "monty 11/14/2013 00:13",
		"startElement:prefix:uri:attributes:" : "JAAyer 3/24/2010 16:47",
		"startElement:prefix:uri:localName:attributes:" : "monty 11/14/2013 00:14",
		"startEntity:" : "JAAyer 11/10/2010 19:22",
		"startInternalSubset" : "monty 10/27/2014 14:45",
		"startPrefixMapping:uri:" : "JAAyer 11/10/2010 19:22",
		"usesNamespaces" : "JAAyer 11/23/2010 14:20",
		"usesNamespaces:" : "monty 12/29/2013 03:03",
		"xmlVersion:encoding:standalone:" : "monty 11/14/2013 00:14" } }
