{
	"class" : {
		"compileHTMLEntityPageWithNamedEntities:" : "monty 12/1/2013 13:25",
		"generateHTMLEntityPage" : "monty 12/7/2013 04:36",
		"htmlEntityPage" : "monty 12/1/2013 13:17",
		"initialize" : "monty 12/19/2013 07:23",
		"initializeHTMLNameDelimiters" : "monty 12/1/2013 00:49",
		"initializePredefinedEntities" : "monty 12/18/2013 23:17",
		"isNonHTMLCodeSectionTag:" : "monty 12/1/2013 01:02",
		"isNonHTMLSectionTag:" : "monty 12/1/2013 01:02" },
	"instance" : {
		"atEnd" : "monty 12/7/2013 03:25",
		"atNonHTMLSectionEndTag" : "monty 11/23/2013 18:23",
		"characterFromCodePoint:" : "monty 12/18/2013 23:16",
		"expectNext:" : "monty 11/22/2013 19:19",
		"expectNextAll:" : "monty 11/22/2013 19:11",
		"expectTerminator:" : "monty 11/22/2013 19:19",
		"expectUpToAll:" : "monty 12/8/2013 04:38",
		"nextAttributeValue" : "monty 12/9/2013 01:34",
		"nextContentMarkupToken" : "monty 12/10/2013 07:27",
		"nextContentToken" : "monty 11/30/2013 07:56",
		"nextEndTag" : "monty 11/30/2013 08:09",
		"nextGeneralEntityReference" : "monty 12/14/2013 02:08",
		"nextName" : "monty 12/14/2013 02:12",
		"nextNonHTMLCodeSectionOn:" : "monty 11/30/2013 21:23",
		"nextNonHTMLSectionToken" : "monty 12/1/2013 01:02",
		"nextPCDataToken" : "monty 12/18/2013 23:19",
		"nextParameterEntityReference" : "monty 12/11/2013 01:49",
		"nextPrologToken" : "monty 12/7/2013 03:53",
		"nextPubidLiteral" : "monty 11/22/2013 10:37",
		"nextQuotedValue" : "monty 12/6/2013 08:36",
		"nextSubsetMarkupToken" : "monty 12/11/2013 02:33",
		"nextSystemLiteralRequired:" : "monty 11/22/2013 10:39",
		"nextTag" : "monty 12/1/2013 01:04",
		"nextValue" : "monty 12/6/2013 08:37",
		"nextXMLDeclAttributeValue" : "monty 12/9/2013 06:53",
		"skipDeclaration" : "monty 12/7/2013 03:33",
		"skipNonDeclarationOrEntity" : "monty 11/22/2013 20:13",
		"tokenContextClass" : "monty 11/23/2013 04:58" } }
